{
  "আরও উজ্জ্বল রাজ্জাক": {
    "title": "আরও উজ্জ্বল রাজ্জাক",
    "description": "প্রিমিয়ার লিগ শুরু করেছিলেন চার উইকেট নিয়ে। পরের তিন ম্যচে নিয়েছেন আরও সাত\nউইকেট। এবার আব্দুর রাজ্জাকের শিকার পাঁচ উইকেট। বোলিংয়ের দাপট অবশ্য ছিল না শেখ\nজামালের ব্যাটিংয়ে। তবে শেষ পর্যন্ত জিতেছে রাজ্জাকের দল।",
    "pubDate": "2017-04-30T14:04:28.000Z",
    "image": "http://d30fl32nd2baj9.cloudfront.net/media/2017/04/30/_f752795.jpg/ALTERNATES/w140/_F752795.JPG",
    "link": "http://bangla.bdnews24.com/cricket/article1327919.bdnews"
  },
  "ঢাকায় শীতাতপ নিয়ন্ত্রণ যন্ত্রে বিস্ফোরণ, দগ্ধ ৪": {
    "title": "ঢাকায় শীতাতপ নিয়ন্ত্রণ যন্ত্রে বিস্ফোরণ, দগ্ধ ৪",
    "description": "ঢাকার এলিফ্যান্ট রোডে বহুতল একটি ভবনের বিস্ফোরণে চারজন দগ্ধ হয়েছেন।",
    "pubDate": "2017-04-30T14:02:41.000Z",
    "image": "none",
    "link": "http://bangla.bdnews24.com/bangladesh/article1327915.bdnews"
  },
  "‘কোয়ান্টাম ডট প্লাস’ প্রযুক্তির টিভি আনছে ওয়ালটন": {
    "title": "‘কোয়ান্টাম ডট প্লাস’ প্রযুক্তির টিভি আনছে ওয়ালটন",
    "description": "টেলিভিশন প্রযুক্তির জগতে ‘কোয়ান্টাম ডট প্লাস’ প্রযুক্তির আগামী প্রজন্মের\n‘স্পেকট্রা কিউ টিভি’ বাজারে আনছে ওয়ালটন।",
    "pubDate": "2017-04-30T14:01:06.000Z",
    "image": "http://d30fl32nd2baj9.cloudfront.net/media/2017/04/30/walton.jpg/ALTERNATES/w140/walton.jpg",
    "link": "http://bangla.bdnews24.com/business/article1327914.bdnews"
  },
  "‘আমার সঙ্গে অন্যায় করা হচ্ছে’": {
    "title": "‘আমার সঙ্গে অন্যায় করা হচ্ছে’",
    "description": "সমিতির সিদ্ধান্তকে উপেক্ষা করে শাকিব খানকে নিয়ে ‘রংবাজ’ সিনেমার দৃশ্যধারণ ও\nসমিতির গঠনতন্ত্রের বিরুদ্ধে অবস্থান নেওয়ার কারণে শনিবার শামীম আহমেদ রনীর সদস্যপদ\nবাতিল ঘোষনা করেছে বাংলাদেশ চলচ্চিত্র পরিচালক সমিতি। এই বিষয়ে রবিবার বিকেলে\nগ্লিটজের মুখোমুখি হয়েছিলেন সাম্প্রতিক সময়ের আলোচিত এই নির্মাতা।",
    "pubDate": "2017-04-30T13:59:25.000Z",
    "image": "http://d30fl32nd2baj9.cloudfront.net/media/2017/04/30/rony-1.jpg/ALTERNATES/w140/rony+1.jpg",
    "link": "http://bangla.bdnews24.com/glitz/article1327912.bdnews"
  },
  "পৃথিবীর যতকিছু": {
    "title": "পৃথিবীর যতকিছু",
    "description": "হাঁসের মতো দেখতে তবে তারা হাঁস নয়, প্লাটিপাস।",
    "pubDate": "2017-04-30T13:54:12.000Z",
    "image": "http://d30fl32nd2baj9.cloudfront.net/media/2017/04/30/wild_platypus_4.jpg/ALTERNATES/w140/Wild_Platypus_4.jpg",
    "link": "http://bangla.bdnews24.com/kidz/article1327907.bdnews"
  },
  "লিটন হত্যা: কাদের খানসহ ৮ জনের বিরুদ্ধে অভিযোগপত্র": {
    "title": "লিটন হত্যা: কাদের খানসহ ৮ জনের বিরুদ্ধে অভিযোগপত্র",
    "description": "গাইবান্ধার সরকার দলীয় সংসদ সদস্য মনজুরুল ইসলাম লিটন হত্যা মামলায় অভিযোগপত্র\nদিয়েছে পুলিশ।",
    "pubDate": "2017-04-30T13:46:29.000Z",
    "image": "http://d30fl32nd2baj9.cloudfront.net/bangla-media/2017/02/25/bogra-kader-khan.jpg/ALTERNATES/w140/BOGRA-Kader-khan.jpg",
    "link": "http://bangla.bdnews24.com/samagrabangladesh/article1327903.bdnews"
  },
  "বরুণের ছবির প্রযোজক ধোনি?": {
    "title": "বরুণের ছবির প্রযোজক ধোনি?",
    "description": "বরুণ ধাওয়ান অভিনয় করবেন- এমন একটি হিন্দি সিনেমা দিয়ে প্রযোজক হিসেবে নতুন ইনিংস\nশুরু করতে যাচ্ছেন সাবেক ভারত অধিনায়ক মহেন্দ্র সিং ধোনি, সম্প্রতি শোনা যাচ্ছে\nএমনই এক গুজব।",
    "pubDate": "2017-04-30T13:35:53.000Z",
    "image": "http://d30fl32nd2baj9.cloudfront.net/media/2017/04/30/dhoni.jpg/ALTERNATES/w140/dhoni.jpg",
    "link": "http://bangla.bdnews24.com/glitz/article1327897.bdnews"
  },
  "শেষ চারের লক্ষ্যে ম্যানইউর হোঁচট": {
    "title": "শেষ চারের লক্ষ্যে ম্যানইউর হোঁচট",
    "description": "সোয়ানসি সিটির কাছে ঘরের মাঠে ড্র করে শীর্ষ চারে থেকে ইংলিশ প্রিমিয়ার লিগ শেষ\nকরার লড়াইয়ে পিছিয়ে পড়েছে ম্যানচেস্টার ইউনাইটেড।",
    "pubDate": "2017-04-30T13:33:15.000Z",
    "image": "http://d30fl32nd2baj9.cloudfront.net/media/2017/04/30/01.jpg/ALTERNATES/w140/01.jpg",
    "link": "http://bangla.bdnews24.com/sport/article1327895.bdnews"
  },
  "পিআইবিএলের সপ্তম প্রতিষ্ঠাবার্ষিকী": {
    "title": "পিআইবিএলের সপ্তম প্রতিষ্ঠাবার্ষিকী",
    "description": "প্রাইম ব্যাংক ইনভেস্টমেন্ট লিমিটেডের (পিবিআইএল) সপ্তম প্রতিষ্ঠাবার্ষিকী উদযাপন\nহল রোববার।",
    "pubDate": "2017-04-30T13:30:25.000Z",
    "image": "http://d30fl32nd2baj9.cloudfront.net/media/2017/04/30/pbil.jpg/ALTERNATES/w140/pbil.JPG",
    "link": "http://bangla.bdnews24.com/business/article1327893.bdnews"
  },
  "কোরিয়া সংকটে আন্তর্জাতিক মধ্যস্থতার আহ্বান পোপের": {
    "title": "কোরিয়া সংকটে আন্তর্জাতিক মধ্যস্থতার আহ্বান পোপের",
    "description": "উত্তর কোরিয়ার পরমাণু প্রকল্প নিয়ে দেশটির সঙ্গে যুক্তরাষ্ট্রের বাড়তে থাকা\nউত্তেজনা প্রশমনে আন্তর্জাতিক মধ্যস্থতার আহ্বান জানিয়েছেন পোপ ফ্রান্সিস।",
    "pubDate": "2017-04-30T13:27:53.000Z",
    "image": "http://d30fl32nd2baj9.cloudfront.net/media/2017/04/30/pope.jpg/ALTERNATES/w140/pope.jpg",
    "link": "http://bangla.bdnews24.com/world/article1327891.bdnews"
  },
  "‘বাহুবলী’র বল্লালদেবের এক চোখ বাস্তবে অন্ধ!": {
    "title": "‘বাহুবলী’র বল্লালদেবের এক চোখ বাস্তবে অন্ধ!",
    "description": "‘বাহুবলী’ সিরিজ দিয়ে আলোচনায় উঠে আসা অভিনেতা রানা দগ্গুবতী একটি অনুষ্ঠানে\nজানিয়েছেন, তিনি ডান চোখে দেখেন না",
    "pubDate": "2017-04-30T13:24:31.000Z",
    "image": "http://d30fl32nd2baj9.cloudfront.net/media/2017/04/30/ballaldev.jpg/ALTERNATES/w140/ballaldev.jpg",
    "link": "http://bangla.bdnews24.com/glitz/article1327890.bdnews"
  },
  "খুলনায় ছাত্রী ‘ধর্ষণ’: সেই টিটোর বিরুদ্ধে গ্রেপ্তারি পরোয়ানা": {
    "title": "খুলনায় ছাত্রী ‘ধর্ষণ’: সেই টিটোর বিরুদ্ধে গ্রেপ্তারি পরোয়ানা",
    "description": "মা ডেকে ঘনিষ্ঠ হয়ে খুলনায় এক কলেজছাত্রীকে ধর্ষণের মামলার একমাত্র আসামির বিরুদ্ধে\nগ্রেপ্তারি পরোয়ানা জারির আদেশ দিয়েছে আদালত।",
    "pubDate": "2017-04-30T13:21:09.000Z",
    "image": "http://d30fl32nd2baj9.cloudfront.net/bangla-media/2017/03/31/handcuff.jpg/ALTERNATES/w140/Handcuff.jpg",
    "link": "http://bangla.bdnews24.com/samagrabangladesh/article1327885.bdnews"
  },
  "ইউপি ভোটের পর মনপুরায় ব্যবসায়ীদের উপর হামলা": {
    "title": "ইউপি ভোটের পর মনপুরায় ব্যবসায়ীদের উপর হামলা",
    "description": "ইউনিয়ন পরিষদ নির্বাচনের পর ভোলার মনপুরায় আক্রান্ত হয়েছেন এক দল হিন্দু ব্যবসায়ী।",
    "pubDate": "2017-04-30T13:20:38.000Z",
    "image": "http://d30fl32nd2baj9.cloudfront.net/media/2017/04/30/monpura-h-pic-2.jpg/ALTERNATES/w140/Monpura-h-pic-2.jpg",
    "link": "http://bangla.bdnews24.com/samagrabangladesh/article1327888.bdnews"
  },
  "লালদীঘির ২৪ হত্যা: ‘তৎকালীন পুলিশ কমিশনারের নির্দেশেই গুলি’": {
    "title": "লালদীঘির ২৪ হত্যা: ‘তৎকালীন পুলিশ কমিশনারের নির্দেশেই গুলি’",
    "description": "ঊনত্রিশ বছর আগে চট্টগ্রামের লালদীঘিতে আওয়ামী লীগ সভানেত্রী শেখ হাসিনার জনসভায়\nযোগ দিতে যাওয়ার পথে তার গাড়ি বহরে তৎকালীন পুলিশ কমিশনার মীর্জা রকিবুল হুদার\nনির্দেশে পুলিশ গুলি চালিয়েছিল বলে অভিযোগ করেছেন এক সাক্ষী।",
    "pubDate": "2017-04-30T13:18:01.000Z",
    "image": "http://d30fl32nd2baj9.cloudfront.net/media/2017/01/24/103_genocide_column_chittan.jpg/ALTERNATES/w140/103_Genocide_Column_Chittan.jpg",
    "link": "http://bangla.bdnews24.com/ctg/article1327886.bdnews"
  },
  "যে দেশে মে দিবসের ইতিহাস ‘ভিন্ন’": {
    "title": "যে দেশে মে দিবসের ইতিহাস ‘ভিন্ন’",
    "description": "পহেলা মে বিশ্বের আনাচে-কানাচে ‘আন্তর্জাতিক শ্রমিক সংহতি দিবস’ হিসেবে পালন হলেও\nএকই দিন ভিন্ন তাৎপর্য ও মাত্রায় উৎসবে মেতে ওঠে গোটা ফিনল্যান্ড। ‘ভাপ্পু দিবস’\nনামে পরিচিত এই দিনকে ঘিরে উৎসবের ব্যাপ্তি ফিনিশদের কাছে বড়দিন ও বর্ষবরণের পরেই।",
    "pubDate": "2017-04-30T13:15:40.000Z",
    "image": "http://d30fl32nd2baj9.cloudfront.net/media/2017/04/30/vappu-may-day1.jpg/ALTERNATES/w140/Vappu-May-Day1.jpg",
    "link": "http://bangla.bdnews24.com/probash/article1327884.bdnews"
  },
  "ফেনসিডিল রাখায় পাঁচজনের যাবজ্জীবন": {
    "title": "ফেনসিডিল রাখায় পাঁচজনের যাবজ্জীবন",
    "description": "ফেনসিডিল রাখার দুই মামলায় পাঁচজনকে যাবজ্জীবন কারাদণ্ডের পাশাপাশি বিভিন্ন অংকের\nঅর্থদণ্ড দিয়েছে ঢাকার একটি আদালত।",
    "pubDate": "2017-04-30T13:14:18.000Z",
    "image": "http://d30fl32nd2baj9.cloudfront.net/media/2015/11/06/102_recover_police_ctg_061115_2.jpg/ALTERNATES/w140/102_Recover_Police_ctg_061115_2.jpg",
    "link": "http://bangla.bdnews24.com/bangladesh/article1327883.bdnews"
  },
  "আরও বেশি গোল করতে পারতাম: লাম": {
    "title": "আরও বেশি গোল করতে পারতাম: লাম",
    "description": "টানা পঞ্চম বুন্ডেসলিগা শিরোপা জয়ের পর বায়ার্ন মিউনিখের কিংবদন্তি ফিলিপ লাম ফিরে\nতাকাচ্ছেন নিজের আলোকিত ক্যারিয়ারের দিকে। ক্লাবটির হয়ে অনেক শিরোপা জিতলেও খুব\nবেশি গোল পাননি তিনি। তাই কিছুটা অতৃপ্ত মৌসুম শেষে অবসর নিতে যাওয়া এই ডিফেন্ডার।",
    "pubDate": "2017-04-30T12:54:27.000Z",
    "image": "http://d30fl32nd2baj9.cloudfront.net/media/2017/04/30/lahm.jpg/ALTERNATES/w140/Lahm.JPG",
    "link": "http://bangla.bdnews24.com/sport/article1327875.bdnews"
  },
  "কোয়ালকম-কে রয়ালটি দিচ্ছে না অ্যাপল": {
    "title": "কোয়ালকম-কে রয়ালটি দিচ্ছে না অ্যাপল",
    "description": "লাইসেন্সিং চুক্তি নিয়ে ‘অমীমাংসিত ঘটনার’ কারণে চিপ নির্মাতা মার্কিন প্রতিষ্ঠান\nকোয়ালকম-কে রয়ালটি দেওয়া বন্ধ করেছে অ্যাপল।",
    "pubDate": "2017-04-30T12:51:52.000Z",
    "image": "http://d30fl32nd2baj9.cloudfront.net/media/2017/04/30/apple-stops-paying-royalties-to-qualcomm.jpg/ALTERNATES/w140/Apple+stops+paying+royalties+to+Qualcomm.jpg",
    "link": "http://bangla.bdnews24.com/tech/article1327873.bdnews"
  },
  "‘প্রতিপক্ষকে ফাঁসাতে মেয়েকে অপহরণ’, মা-বাবা গ্রেপ্তার": {
    "title": "‘প্রতিপক্ষকে ফাঁসাতে মেয়েকে অপহরণ’, মা-বাবা গ্রেপ্তার",
    "description": "নিজেদের সাড়ে তিন বছরের মেয়েকে ‘লুকিয়ে রেখে’ প্রতিপক্ষের বিরুদ্ধে অপহরণের দোষ\nচাপানোর অভিযোগ উঠেছে মা ও বাবার বিরুদ্ধে।",
    "pubDate": "2017-04-30T12:51:00.000Z",
    "image": "http://d30fl32nd2baj9.cloudfront.net/media/2017/04/30/bogra.jpg/ALTERNATES/w140/Bogra.JPG",
    "link": "http://bangla.bdnews24.com/samagrabangladesh/article1327870.bdnews"
  },
  "অসচ্ছল শিক্ষার্থীদের বৃত্তি দিল শাহ্জালাল ব্যাংক": {
    "title": "অসচ্ছল শিক্ষার্থীদের বৃত্তি দিল শাহ্জালাল ব্যাংক",
    "description": "দেশের বিভিন্ন কলেজ, মেডিকেল কলেজ ও বিশ্ববিদ্যালয়ে অধ্যয়নরত অসচ্ছল ৫০০\nশিক্ষার্থীকে বৃত্তি দিয়েছে শাহ্জালাল ইসলামী ব্যাংক লিমিটেড।",
    "pubDate": "2017-04-30T12:49:05.000Z",
    "image": "http://d30fl32nd2baj9.cloudfront.net/media/2017/04/30/sjibl.jpg/ALTERNATES/w140/sjibl.JPG",
    "link": "http://bangla.bdnews24.com/business/article1327867.bdnews"
  },
  "তিনশ কোটির পথে ‘বাহুবলী টু’": {
    "title": "তিনশ কোটির পথে ‘বাহুবলী টু’",
    "description": "প্রথম দিনেই সর্বকালের সেরা উদ্বোধনী আয়ের রেকর্ড গড়ার পর এস.এস রাজামৌলি’র\n‘বাহুবলী টু : দ্য কনক্লুশন’ এবার ধেয়ে চলেছে তিনশ কোটি রুপি আয়ের পথে। প্রথম দুই\nদিনেই ২৮৫ কোটি ‍রুপি আয় করেছে সিনেমাটি।",
    "pubDate": "2017-04-30T12:48:33.000Z",
    "image": "http://d30fl32nd2baj9.cloudfront.net/media/2017/04/30/bahubali-1.jpg/ALTERNATES/w140/bahubali+1.jpg",
    "link": "http://bangla.bdnews24.com/glitz/article1327866.bdnews"
  },
  "সিঙ্গাপুরের চিঠি: গৃহকর্মী সমাচার": {
    "title": "সিঙ্গাপুরের চিঠি: গৃহকর্মী সমাচার",
    "description": "সিঙ্গাপুরে আসার পর যে মেয়েটির সাথে আমার সবচেয়ে বেশি সখ্যতা গড়ে উঠেছিল তার নাম\nপারভিন (ছদ্মনাম)। সে ইন্দোনেশিয়ার নাগরিক।",
    "pubDate": "2017-04-30T12:45:35.000Z",
    "image": "http://d30fl32nd2baj9.cloudfront.net/media/2017/04/30/housemaid-1.jpg/ALTERNATES/w140/Housemaid+1.jpg",
    "link": "http://bangla.bdnews24.com/probash/article1327862.bdnews"
  },
  "জুরাইন কবরস্থানে সাংবাদিক ওমর ফারুকের দাফন": {
    "title": "জুরাইন কবরস্থানে সাংবাদিক ওমর ফারুকের দাফন",
    "description": "অনলাইন নিউজ পোর্টাল বাংলা ট্রিবিউনের বিশেষ প্রতিনিধি ওমর ফারুককে রাজধানীর জুরাইন\nকবরস্থানে দাফন করা হয়েছে।",
    "pubDate": "2017-04-30T12:42:04.000Z",
    "image": "http://d30fl32nd2baj9.cloudfront.net/media/2017/04/30/omar-farook.jpg1/ALTERNATES/w140/omar-farook.jpg",
    "link": "http://bangla.bdnews24.com/bangladesh/article1327858.bdnews"
  },
  "মে দিবসে ‘চিৎকার’-এর মিউজিক ভিডিও": {
    "title": "মে দিবসে ‘চিৎকার’-এর মিউজিক ভিডিও",
    "description": "মহান মে দিবস উপলক্ষ্যে নিজেদের গানের মিউজিক ভিডিও প্রকাশ করতে যাচ্ছে ব্যান্ডদল\n‘চিৎকার’।",
    "pubDate": "2017-04-30T12:31:14.000Z",
    "image": "http://d30fl32nd2baj9.cloudfront.net/media/2017/04/30/chitkar-1.jpg/ALTERNATES/w140/chitkar+1.jpg",
    "link": "http://bangla.bdnews24.com/glitz/article1327855.bdnews"
  },
  "বিশ্ব জাকের মঞ্জিলে ফাতেহা শুরু রোববার": {
    "title": "বিশ্ব জাকের মঞ্জিলে ফাতেহা শুরু রোববার",
    "description": "হযরত শাহসুফি খাজাবাবা ফরিদপুরীর দুই দিনব্যাপী বিশ্ব ফাতেহা শরীফ শুরু হচ্ছে\nরোববার।",
    "pubDate": "2017-04-30T12:29:15.000Z",
    "image": "http://d30fl32nd2baj9.cloudfront.net/media/2017/04/30/faridpur-jaker-monjil.jpg/ALTERNATES/w140/Faridpur-Jaker-monjil.jpg",
    "link": "http://bangla.bdnews24.com/samagrabangladesh/article1327852.bdnews"
  },
  "কিছু দলের বক্তব্য জঙ্গিদের পক্ষে যায়: আইজিপি": {
    "title": "কিছু দলের বক্তব্য জঙ্গিদের পক্ষে যায়: আইজিপি",
    "description": "জঙ্গি দমনে আইন-শৃঙ্খলা বাহিনীর অভিযান নিয়ে বিএনপি নেতাদের সন্দেহের জবাব এসেছে\nপুলিশ মহাপরিদর্শক একেএম শহীদুল হকের কথায়।",
    "pubDate": "2017-04-30T12:28:39.000Z",
    "image": "http://d30fl32nd2baj9.cloudfront.net/media/2016/08/18/igp-akm-shahidul-hoque_2003.jpg/ALTERNATES/w140/IGP-AKM-Shahidul-Hoque_2003.jpg",
    "link": "http://bangla.bdnews24.com/bangladesh/article1327849.bdnews"
  },
  "১৫ মে বাংলাদেশে আসছেন রিচার্ড মার্কস": {
    "title": "১৫ মে বাংলাদেশে আসছেন রিচার্ড মার্কস",
    "description": "বাংলাদেশে আসছেন বিশ্ববিখ্যাত সংগীত তারকা রিচার্ড মার্কস। ঢাকায় এক কনসার্টে অংশ\nনিতে আগামী ১৫ মে ঢাকায় উপস্থিত হচ্ছেন তিনি।",
    "pubDate": "2017-04-30T12:26:33.000Z",
    "image": "http://d30fl32nd2baj9.cloudfront.net/media/2017/04/30/richerd-marx.jpg/ALTERNATES/w140/richerd+marx.jpg",
    "link": "http://bangla.bdnews24.com/glitz/article1327848.bdnews"
  },
  "দেশে ফিরছেন মাশরাফি": {
    "title": "দেশে ফিরছেন মাশরাফি",
    "description": "ইংল্যান্ড গিয়ে মাত্র দুদিন অনুশীলন করতে পেরেছেন। এরপরই দেশের পথে মাশরাফি বিন\nমুর্তজা। হঠাৎ অসুস্থ হয়ে হাসপাতালে স্ত্রী। খবর পেয়ে বাংলাদেশ অধিনায়ক রওনা হয়েছেন\nদেশে।",
    "pubDate": "2017-04-30T12:24:09.000Z",
    "image": "http://d30fl32nd2baj9.cloudfront.net/media/2017/04/05/01.jpg1/ALTERNATES/w140/01.jpg",
    "link": "http://bangla.bdnews24.com/cricket/article1327846.bdnews"
  },
  "ব্রাদার্সকে জেতালেন মাইশুকুর-ফরহাদ": {
    "title": "ব্রাদার্সকে জেতালেন মাইশুকুর-ফরহাদ",
    "description": "দারুণ অপরাজিত ইনিংসে দলকে টানলেন মাইশকুর রহমান। সঙ্গ দিলেন ফরহাদ হোসেন। শেষ দিকে\nঝড়ো ইনিংস খেললেন ধীমান ঘোষ। বল হাতে আবার সফল তরুণ স্পিনার নিহাদুজ্জামান। আবার\nজয়ের মুখ দেখল ব্রাদার্স।",
    "pubDate": "2017-04-30T12:22:17.000Z",
    "image": "http://d30fl32nd2baj9.cloudfront.net/media/2017/04/30/myshukur.jpg/ALTERNATES/w140/MYshukur.jpg",
    "link": "http://bangla.bdnews24.com/cricket/article1327845.bdnews"
  },
  "জিরাবোতে ভিশন এম্পোরিয়ামের শোরুম": {
    "title": "জিরাবোতে ভিশন এম্পোরিয়ামের শোরুম",
    "description": "আরএফএল গ্রুপের ইলেকট্রনিক পণ্যের রিটেইল চেইনশপ ভিশন এম্পোরিয়াম সাভারের জিরাবোতে\nএকটি আউটলেট চালু করেছে।",
    "pubDate": "2017-04-30T12:13:44.000Z",
    "image": "http://d30fl32nd2baj9.cloudfront.net/media/2017/04/30/vision.jpg/ALTERNATES/w140/Vision.JPG",
    "link": "http://bangla.bdnews24.com/business/article1327842.bdnews"
  },
  "মেজর জেনারেল পাশা হাবিব আনসারের নতুন মহাপরিচালক": {
    "title": "মেজর জেনারেল পাশা হাবিব আনসারের নতুন মহাপরিচালক",
    "description": "মেজর জেনারেল শেখ পাশা হাবিব উদ্দিনকে আনসার ও গ্রাম প্রতিরক্ষা বাহিনীর মহাপরিচালক\nহিসেবে নিয়োগ দিয়েছে সরকার।",
    "pubDate": "2017-04-30T12:11:24.000Z",
    "image": "none",
    "link": "http://bangla.bdnews24.com/bangladesh/article1327838.bdnews"
  },
  "৮০% শ্রমিককে দিনে ৮ ঘণ্টার বেশি কাজ করানো হয়: বিলস": {
    "title": "৮০% শ্রমিককে দিনে ৮ ঘণ্টার বেশি কাজ করানো হয়: বিলস",
    "description": "বাংলাদেশের শ্রম আইনে দৈনিক কর্মঘণ্টা আট ঘণ্টা নির্ধারিত থাকলেও অন্তত ৮০ শতাংশ\nশ্রমিককে তার বেশি সময় কাজ করানো হয় বলে দাবি করেছে বাংলাদেশ ইনস্টিটিউট অব লেবার\nস্টাডিজ (বিলস)।",
    "pubDate": "2017-04-30T12:05:37.000Z",
    "image": "http://d30fl32nd2baj9.cloudfront.net/media/2017/04/30/bils_workplace_situation.jpg/ALTERNATES/w140/BILS_Workplace_Situation.jpg",
    "link": "http://bangla.bdnews24.com/bangladesh/article1327829.bdnews"
  },
  "৬ কোম্পানির লভ্যাংশ ঘোষণা": {
    "title": "৬ কোম্পানির লভ্যাংশ ঘোষণা",
    "description": "পুঁজিবাজারে তালিকাভুক্ত ছয়টি কোম্পানির পরিচালনা পর্ষদ শেয়ারহোল্ডারদের জন্য গত\nবছরের লভ্যাংশ ঘোষণা করেছে।",
    "pubDate": "2017-04-30T11:53:19.000Z",
    "image": "http://d30fl32nd2baj9.cloudfront.net/media/2016/06/19/dhaka-stock-excahnge0001.jpg/ALTERNATES/w140/Dhaka+Stock+Excahnge0001.jpg",
    "link": "http://bangla.bdnews24.com/stocks/article1327821.bdnews"
  },
  "ফরমুলা বাদ দেন, ভোটের জন্য প্রস্তুত হন: নাসিম": {
    "title": "ফরমুলা বাদ দেন, ভোটের জন্য প্রস্তুত হন: নাসিম",
    "description": "প্রধানমন্ত্রী শেখ হাসিনার অধীনেই আগামী নির্বাচন হবে বলে তাতে অংশ নেওয়ার জন্য\nবিএনপিকে প্রস্তুতি নিতে বলেছেন আওয়ামী লীগনেতা মোহাম্মদ নাসিম।",
    "pubDate": "2017-04-30T11:47:02.000Z",
    "image": "http://d30fl32nd2baj9.cloudfront.net/media/2015/10/29/05_mohammed-nasim_amo_291015_0016.jpg/ALTERNATES/w140/05_Mohammed+Nasim_AMO_291015_0016.jpg",
    "link": "http://bangla.bdnews24.com/politics/article1327820.bdnews"
  },
  "সাব্বির ‘আত্মহত্যা’ করেছেন, বলছেন চিকিৎসক": {
    "title": "সাব্বির ‘আত্মহত্যা’ করেছেন, বলছেন চিকিৎসক",
    "description": "রাজশাহী মহানগর পুলিশের সহকারী কমিশনার সাব্বির আহমেদ সরফরাজ আত্মহত্যা করেছেন বলে\nজানিয়েছেন ময়নাতদন্তকারী চিকিৎসক।",
    "pubDate": "2017-04-30T11:45:14.000Z",
    "image": "http://d30fl32nd2baj9.cloudfront.net/media/2017/04/29/rajshahi-ac-suicide-2.jpg/ALTERNATES/w140/Rajshahi-AC-suicide-2.jpg",
    "link": "http://bangla.bdnews24.com/samagrabangladesh/article1327819.bdnews"
  },
  "হ্যাকিংয়ের শিকার নেটফ্লিক্স": {
    "title": "হ্যাকিংয়ের শিকার নেটফ্লিক্স",
    "description": "স্ট্রিমিং ভিডিও সেবাদাতা প্রতিষ্ঠান নেটফ্লিক্স-এ হ্যাকিং চালিয়ে টিভি সিরিজ\n‘অরেঞ্জ ইজ দ্য নিউ ব্ল্যাক’-এর নতুন মৌসুমের পর্বগুলো হাতিয়ে নিয়েছে অপরিচিত এক\nহ্যাকার।",
    "pubDate": "2017-04-30T11:43:48.000Z",
    "image": "http://d30fl32nd2baj9.cloudfront.net/media/2017/04/30/a-hacker-says-it-has-the-new-season-of-netflix-s-orange-is-the-new-black-.jpg/ALTERNATES/w140/A+hacker+says+it+has+the+new+season+of+Netflix%27s+%27Orange+is+the+New+Black%27.jpg",
    "link": "http://bangla.bdnews24.com/tech/article1327818.bdnews"
  },
  "রংপুরে মাদক মামলায় তিনজনের যাবজ্জীবন": {
    "title": "রংপুরে মাদক মামলায় তিনজনের যাবজ্জীবন",
    "description": "রংপুরে পাঁচ বছরের আগে এক মাদক মামলায় তিনজনকে যাবজ্জীবন কারাদণ্ড দিয়েছে আদালত।",
    "pubDate": "2017-04-30T11:40:59.000Z",
    "image": "http://d30fl32nd2baj9.cloudfront.net/bangla-media/2017/04/25/justice-tm.jpg1/ALTERNATES/w140/justice-tm.jpg",
    "link": "http://bangla.bdnews24.com/samagrabangladesh/article1327816.bdnews"
  },
  "রহস্যময় স্যাটেলাইট পাঠাচ্ছে স্পেসএক্স": {
    "title": "রহস্যময় স্যাটেলাইট পাঠাচ্ছে স্পেসএক্স",
    "description": "রোববার মার্কিন গোয়েন্দা সংস্থার জন্য রহস্যময় একটি স্যাটেলাইট উৎক্ষেপণ করতে\nযাচ্ছে ইলন মাস্কের নভোযান নির্মাতা প্রতিষ্ঠান স্পেসএক্স।",
    "pubDate": "2017-04-30T11:40:57.000Z",
    "image": "http://d30fl32nd2baj9.cloudfront.net/media/2017/04/30/spacex-to-launch-secretive-satellite-for-u.jpg/ALTERNATES/w140/SpaceX+to+launch+secretive+satellite+for+U.jpg",
    "link": "http://bangla.bdnews24.com/tech/article1327815.bdnews"
  },
  "স্পিনে উজ্জ্বল তাইজুল-এনামুল, ব্যাটে-বলে শামসুর": {
    "title": "স্পিনে উজ্জ্বল তাইজুল-এনামুল, ব্যাটে-বলে শামসুর",
    "description": "স্পিনে জ্বলে উঠলেন তাইজুল ইসলাম ও এনামুল হক জুনিয়র। ব্যাটসম্যান শামসুর রহমান বনে\nগেলেন অলরাউন্ডার। এই ত্রয়ীর দুর্দান্ত পারফরম্যান্সে ভিক্টোরিয়াকে উড়িয়ে দিল\nমোহামেডান।",
    "pubDate": "2017-04-30T11:39:44.000Z",
    "image": "http://d30fl32nd2baj9.cloudfront.net/media/2017/04/30/taijul.jpg/ALTERNATES/w140/Taijul.JPG",
    "link": "http://bangla.bdnews24.com/cricket/article1327814.bdnews"
  },
  "আর বাড়ি বাড়ি গিয়ে বেচবে না সোলারসিটি": {
    "title": "আর বাড়ি বাড়ি গিয়ে বেচবে না সোলারসিটি",
    "description": "প্রতিষ্ঠানকে উন্নত মানে ব্র্যান্ডে পরিণত করার লক্ষ্যে চলতি বছর মে মাস থেকে বাড়ি\nবাড়ি গিয়ে ছাদে সৌরপ্যানেল স্থাপন কমিয়ে দেবে সোলারসিটি, শুক্রবার এ তথ্য প্রকাশ\nকরে সৌরপ্যানেল সরবরাহকারী প্রতিষ্ঠানটির মালিক প্রতিষ্ঠান টেসলা।",
    "pubDate": "2017-04-30T11:36:02.000Z",
    "image": "http://d30fl32nd2baj9.cloudfront.net/media/2017/04/30/tesla-says-it-will-stop-selling-solar-door-to-door.jpg/ALTERNATES/w140/Tesla+says+it+will+stop+selling+solar+door-to-door.jpg",
    "link": "http://bangla.bdnews24.com/tech/article1327809.bdnews"
  },
  "বাংলাদেশ এখন ফরমালিনমুক্ত: বাণিজ্যমন্ত্রী": {
    "title": "বাংলাদেশ এখন ফরমালিনমুক্ত: বাণিজ্যমন্ত্রী",
    "description": "বাংলাদেশে এখন ফল, শাক-সবজি কিংবা মাছ সংরক্ষণে ফরমালিন ব্যবহারের কোনো সুযোগ নেই\nবলে দাবি করেছেন বাণিজ্যমন্ত্রী তোফায়েল আহমেদ।",
    "pubDate": "2017-04-30T11:26:19.000Z",
    "image": "none",
    "link": "http://bangla.bdnews24.com/business/article1327806.bdnews"
  },
  "ভুল তথ্যে হৃদযন্ত্রে রিং বসানোর চেষ্টা, দুই আসামির জামিন": {
    "title": "ভুল তথ্যে হৃদযন্ত্রে রিং বসানোর চেষ্টা, দুই আসামির জামিন",
    "description": "ভুল তথ্য দিয়ে হৃদযন্ত্রে রিং বসাতে (এনজিওপ্লাস্টি) রোগীকে বাধ্য করার চেষ্টার\nমামলায় চিকিৎসক রাকিবুল ইসলাম লিটুসহ দুজন জামিন পেয়েছেন।",
    "pubDate": "2017-04-30T10:56:48.000Z",
    "image": "none",
    "link": "http://bangla.bdnews24.com/bangladesh/article1327798.bdnews"
  },
  "স্ত্রীর মামলায় কারাগারে পটিয়ার সাবেক ওসি": {
    "title": "স্ত্রীর মামলায় কারাগারে পটিয়ার সাবেক ওসি",
    "description": "স্ত্রীর করা নির্যাতনের মামলায় কারাগারে পাঠানো হয়েছে চট্টগ্রামের পটিয়া থানার\nসাবেক ওসি রেফায়েত উল্লাহ চৌধুরীকে।",
    "pubDate": "2017-04-30T10:55:13.000Z",
    "image": "http://d30fl32nd2baj9.cloudfront.net/media/2017/04/30/khulna-picture-30.04.14.jpg/ALTERNATES/w140/Khulna-picture-30.04.14.jpg",
    "link": "http://bangla.bdnews24.com/samagrabangladesh/article1327797.bdnews"
  },
  "রমজানে স্থিতিশীল থাকবে পণ্যের দাম, আশা বাণিজ্যমন্ত্রীর": {
    "title": "রমজানে স্থিতিশীল থাকবে পণ্যের দাম, আশা বাণিজ্যমন্ত্রীর",
    "description": "ডলারের মূল্য বৃদ্ধির কারণে কয়েকটি পণ্যের দাম বাড়লেও পর্যাপ্ত মজুদ থাকায় রমজানে\nতা স্থিতিশীল হবে বলে আশা করছেন বাণিজ্য মন্ত্রী তোফায়েল আহমেদ।",
    "pubDate": "2017-04-30T10:49:58.000Z",
    "image": "http://d30fl32nd2baj9.cloudfront.net/media/2014/03/23/06_tofail-ahmed_bangladesh-furniture-interior-decor-expo_230314_0026.jpg/ALTERNATES/w140/06_Tofail+Ahmed_Bangladesh+Furniture+%26+Interior+Decor+EXPO_230314_0026.jpg",
    "link": "http://bangla.bdnews24.com/business/article1327794.bdnews"
  },
  "দোষী সাব্যস্ত না হলে রাজাকার বলা সমীচীন নয়: ট্রাইব্যুনাল": {
    "title": "দোষী সাব্যস্ত না হলে রাজাকার বলা সমীচীন নয়: ট্রাইব্যুনাল",
    "description": "আন্তর্জাতিক অপরাধ ট্রাইব্যুনাল বলেছে, যুদ্ধাপরাধের মামলায় দোষী সাব্যস্ত না হওয়া\nপর্যন্ত কোনো আসামিকে ‘রাজাকার’ বলা সমীচীন হবে না।",
    "pubDate": "2017-04-30T10:38:08.000Z",
    "image": "http://d30fl32nd2baj9.cloudfront.net/media/2016/02/09/10_tribunal_020216_0017.jpg/ALTERNATES/w140/10_tribunal_020216_0017.jpg",
    "link": "http://bangla.bdnews24.com/bangladesh/article1327788.bdnews"
  },
  "পুঁজিবাজারে সূচক, লেনদেন কমেছে": {
    "title": "পুঁজিবাজারে সূচক, লেনদেন কমেছে",
    "description": "সপ্তাহের প্রথম কার্যদিবসে বাংলাদেশের দুই পুঁজিবাজারেই মূল্যসূচক ও লেনদেন কমেছে।",
    "pubDate": "2017-04-30T10:36:15.000Z",
    "image": "http://d30fl32nd2baj9.cloudfront.net/media/2017/04/30/dse.jpg/ALTERNATES/w140/DSE.jpg",
    "link": "http://bangla.bdnews24.com/stocks/article1327787.bdnews"
  },
  "মে দিবসের শুভেচ্ছা জানিয়ে খালেদার টুইট": {
    "title": "মে দিবসের শুভেচ্ছা জানিয়ে খালেদার টুইট",
    "description": "মে দিবস উপলক্ষে শ্রমজীবীদের শুভেচ্ছা জানিয়ে টুইট করেছেন খালেদা জিয়া।",
    "pubDate": "2017-04-30T10:23:04.000Z",
    "image": "http://d30fl32nd2baj9.cloudfront.net/media/2016/11/18/01_khaleda-zia_bnp_westin_ap_181116_0009.jpg1/ALTERNATES/w140/01_Khaleda+Zia_BNP_Westin_AP_181116_0009.jpg",
    "link": "http://bangla.bdnews24.com/politics/article1327784.bdnews"
  },
  "আ. লীগ নাজেহাল করছে: ফখরুল": {
    "title": "আ. লীগ নাজেহাল করছে: ফখরুল",
    "description": "বিএনপির মহাসচিব মির্জা ফখরুল ইসলাম আলমগীর বলেছেন, পুরনো রাজনৈতিক দল হওয়ায় আওয়ামী\nলীগ অন্যান্য রাজনৈতিক দলগুলোকে সম্মান ও সমীহ করবে বলে আশা করেছিলেন।",
    "pubDate": "2017-04-30T10:22:22.000Z",
    "image": "http://d30fl32nd2baj9.cloudfront.net/media/2017/04/30/thakurgaon-mirza-fakhrul-pi.jpg/ALTERNATES/w140/Thakurgaon-Mirza-Fakhrul-Pi.jpg",
    "link": "http://bangla.bdnews24.com/samagrabangladesh/article1327783.bdnews"
  },
  "এলটিইর সফল পরীক্ষা চালিয়েছে রবি ও এরিকসন": {
    "title": "এলটিইর সফল পরীক্ষা চালিয়েছে রবি ও এরিকসন",
    "description": "মোবাইল ফোন অপারেটর রবি ও টেলিযোগাযোগ সরঞ্জাম প্রস্তুতকারক প্রতিষ্ঠান এরিকসন\nসম্প্রতি রাজধানীতে ‘লং টার্ম ইভাল্যুয়েশন (এলটিই) প্রযুক্তির সফল পরীক্ষা\nচালিয়েছে।",
    "pubDate": "2017-04-30T10:19:41.000Z",
    "image": "http://d30fl32nd2baj9.cloudfront.net/media/2017/04/30/robi-lte--1-.jpg/ALTERNATES/w140/ROBI-LTE-%281%29.jpg",
    "link": "http://bangla.bdnews24.com/business/article1327779.bdnews"
  },
  "তাইওয়ানে ৩৯তম সিদ্দিকুর": {
    "title": "তাইওয়ানে ৩৯তম সিদ্দিকুর",
    "description": "সব মিলিয়ে পারের চেয়ে দুই শট কম খেলে ইয়েঙ্গডার হেরিটেজ ওপেনে পাঁচ জনের সঙ্গে\nযৌথভাবে ৩৯তম হয়েছেন বাংলাদেশের সিদ্দিকুর রহমান।",
    "pubDate": "2017-04-30T10:08:12.000Z",
    "image": "http://d30fl32nd2baj9.cloudfront.net/media/2017/04/30/siddikur.jpg/ALTERNATES/w140/Siddikur.jpg",
    "link": "http://bangla.bdnews24.com/sport/article1327770.bdnews"
  }
}
